compyc/compyc.py
compyc-0.1.26.dist-info/LICENSE
compyc-0.1.26.dist-info/METADATA
compyc-0.1.26.dist-info/WHEEL
compyc-0.1.26.dist-info/entry_points.txt
compyc-0.1.26.dist-info/top_level.txt
compyc-0.1.26.dist-info/RECORD
