Metadata-Version: 2.1
Name: compyc
Version: 0.1.26
Home-page: https://github.com/gaofengg/compyc
Author: GaoFeng
Author-email: ymmtd@163.com
Project-URL: Bug Tracker, https://github.com/gaofengg/compyc/issues
Classifier: Programming Language :: Python :: 3
Classifier: License :: OSI Approved :: MIT License
Classifier: Operating System :: OS Independent
Requires-Python: >=3.6
License-File: LICENSE
Requires-Dist: Click
